dingtalk/__init__.py
dingtalk/example/__init__.py
dingtalk/example/client_test.py
dingtalk/example/utils_test.py
dingtalk/src/__init__.py
dingtalk/src/dingtalk_client.py
dingtalk/src/dingtalk_utils.py
dingtalk_lite-1.0.2.dist-info/METADATA
dingtalk_lite-1.0.2.dist-info/WHEEL
dingtalk_lite-1.0.2.dist-info/top_level.txt
dingtalk_lite-1.0.2.dist-info/RECORD
