Metadata-Version: 2.1
Name: dingtalk-lite
Version: 1.0.2
Summary: Lite SDK for Dingtalk
Home-page: http://example.com
Author: Seamus
Author-email: seamusmore@163.com
License: MIT
Keywords: dingtalk,dingding
Platform: UNKNOWN
Requires-Dist: requests
